ays_agent/__init__.py
ays_agent/__main__.py
ays_agent/cli.py
ays_agent/stat/__init__.py
ays_agent/stat/cpu.py
ays_agent/stat/disk.py
ays_agent/stat/memory.py
ays_agent/stat/network.py
tests/__init__.py
tests/context.py
tests/test_agent.py
ays_agent-1.1.dist-info/LICENSE
ays_agent-1.1.dist-info/METADATA
ays_agent-1.1.dist-info/WHEEL
ays_agent-1.1.dist-info/entry_points.txt
ays_agent-1.1.dist-info/top_level.txt
ays_agent-1.1.dist-info/RECORD
