Metadata-Version: 2.1
Name: ays_agent
Version: 1.1
Summary: @ys Agent Sensor
Classifier: Programming Language :: Python :: 3
Classifier: License :: OSI Approved :: MIT License
Classifier: Operating System :: OS Independent
License-File: LICENSE
Requires-Dist: click >=7.1.2
Requires-Dist: fastapi >=0.109.1
Requires-Dist: fastapi-utils >=0.2.1
Requires-Dist: psutil >=5.9.5
Requires-Dist: PyYaml >=6.0
Requires-Dist: requests >=2.31.0
Requires-Dist: rich >=13.7.0
Requires-Dist: typer >=0.9.0
Requires-Dist: urllib3 <2,>=1.26.18
Requires-Dist: uvicorn >=0.18.3
